<?xml version="1.0" encoding="utf-8"?>
<ConfigModel xmlns:xsd="http://www.w3.org/2001/XMLSchema" xmlns:xsi="http://www.w3.org/2001/XMLSchema-instance">
    <SkipCmdletGeneration>false</SkipCmdletGeneration>
    <C2jFilename>acm-pca</C2jFilename>
    <SourceGenerationRoot>AmazonCertificateManagerPCA</SourceGenerationRoot>
    <ServiceNounPrefix>PCA</ServiceNounPrefix>
    <ServiceName>AWS Certificate Manager Private Certificate Authority</ServiceName>
    <ServiceClientInterface>IAmazonACMPCA</ServiceClientInterface>
    <ServiceClient>AmazonACMPCAClient</ServiceClient>
    <ServiceNamespace>Amazon.ACMPCA</ServiceNamespace>
    <PipelineParameter />
    <AutoIterate Start="NextToken" Next="NextToken" EmitLimit="MaxResults" ServicePageSize="-1" />
    <VerbMappings />
    <NounMappings />
    <Params />
    <AdditionalNamespaces />
    <CustomAliases />
    <LegacyAliases />
    <ParamEmitters />
    <MetadataProperties />
    <PipelineByNameProperties />
    <ServiceOperations>
        <ServiceOperation MethodName="CreateCertificateAuthority" Output="DefaultSingleMember" Verb="New" Noun="CertificateAuthority" AnonymousShouldProcessTarget="true" PipelineParameter="" NoPipelineParameter="true">
            <Params />
        </ServiceOperation>
        <ServiceOperation MethodName="CreateCertificateAuthorityAuditReport" Output="Response" Verb="New" Noun="CertificateAuthorityAuditReport" ShouldProcessTarget="CertificateAuthorityArn" PipelineParameter="CertificateAuthorityArn" NoPipelineParameter="false">
            <Params />
        </ServiceOperation>
        <ServiceOperation MethodName="DeleteCertificateAuthority" Output="Void" Verb="Remove" Noun="CertificateAuthority" ShouldProcessTarget="CertificateAuthorityArn" PipelineParameter="CertificateAuthorityArn" NoPipelineParameter="false">
            <Params />
        </ServiceOperation>
        <ServiceOperation MethodName="DescribeCertificateAuthority" Output="DefaultSingleMember" Verb="Get" Noun="CertificateAuthority" PipelineParameter="CertificateAuthorityArn" NoPipelineParameter="false">
            <Params />
        </ServiceOperation>
        <ServiceOperation MethodName="DescribeCertificateAuthorityAuditReport" Output="Response" Verb="Get" Noun="CertificateAuthorityAuditReport" PipelineParameter="AuditReportId" NoPipelineParameter="false">
            <Params />
        </ServiceOperation>
        <ServiceOperation MethodName="GetCertificate" Output="Response" Verb="Get" Noun="Certificate" PipelineParameter="CertificateArn" NoPipelineParameter="false">
            <Params />
        </ServiceOperation>
        <ServiceOperation MethodName="GetCertificateAuthorityCertificate" Output="Response" Verb="Get" Noun="CertificateAuthorityCertificate" PipelineParameter="CertificateAuthorityArn" NoPipelineParameter="false">
            <Params />
        </ServiceOperation>
        <ServiceOperation MethodName="GetCertificateAuthorityCsr" Output="DefaultSingleMember" Verb="Get" Noun="CertificateAuthorityCsr" PipelineParameter="CertificateAuthorityArn" NoPipelineParameter="false">
            <Params />
        </ServiceOperation>
        <ServiceOperation MethodName="ImportCertificateAuthorityCertificate" Output="Void" Verb="Import" Noun="CertificateAuthorityCertificate" ShouldProcessTarget="CertificateAuthorityArn" PipelineParameter="CertificateAuthorityArn" NoPipelineParameter="false">
            <Params />
        </ServiceOperation>
        <ServiceOperation MethodName="IssueCertificate" Output="DefaultSingleMember" Verb="New" Noun="Certificate" ShouldProcessTarget="CertificateAuthorityArn" PipelineParameter="CertificateAuthorityArn" NoPipelineParameter="false">
            <Params />
        </ServiceOperation>
        <ServiceOperation MethodName="ListCertificateAuthorities" Output="DefaultSingleMember" Verb="Get" Noun="CertificateAuthorityList" PipelineParameter="" NoPipelineParameter="false">
            <Params />
        </ServiceOperation>
        <ServiceOperation MethodName="ListTags" Output="DefaultSingleMember" Verb="Get" Noun="CertificateAuthorityTagList" PipelineParameter="CertificateAuthorityArn" NoPipelineParameter="false">
            <Params />
        </ServiceOperation>
        <ServiceOperation MethodName="RestoreCertificateAuthority" Output="Void" Verb="Restore" Noun="CertificateAuthority" ShouldProcessTarget="CertificateAuthorityArn" PipelineParameter="CertificateAuthorityArn" NoPipelineParameter="false">
            <Params />
        </ServiceOperation>
        <ServiceOperation MethodName="RevokeCertificate" Output="Void" Verb="Revoke" Noun="Certificate" ShouldProcessTarget="CertificateAuthorityArn" PipelineParameter="CertificateAuthorityArn" NoPipelineParameter="false">
            <Params />
        </ServiceOperation>
        <ServiceOperation MethodName="TagCertificateAuthority" Output="Void" Verb="Add" Noun="CertificateAuthorityTag" ShouldProcessTarget="CertificateAuthorityArn" PipelineParameter="CertificateAuthorityArn" NoPipelineParameter="false">
            <Params />
        </ServiceOperation>
        <ServiceOperation MethodName="UntagCertificateAuthority" Output="Void" Verb="Remove" Noun="CertificateAuthorityTag" ShouldProcessTarget="CertificateAuthorityArn" PipelineParameter="CertificateAuthorityArn" NoPipelineParameter="false">
            <Params />
        </ServiceOperation>
        <ServiceOperation MethodName="UpdateCertificateAuthority" Output="Void" Verb="Update" Noun="CertificateAuthority" ShouldProcessTarget="CertificateAuthorityArn" PipelineParameter="CertificateAuthorityArn" NoPipelineParameter="false">
            <Params />
        </ServiceOperation>
    </ServiceOperations>
    <InputObjectMappingRules />
    <SupportsShouldProcessVerbs />
    <TypesNotToFlatten>
        <Type>Amazon.ACMPCA.Model.CertificateAuthorityConfiguration</Type>
        <Type>Amazon.ACMPCA.Model.RevocationConfiguration</Type>
        <Type>Amazon.ACMPCA.Model.Validity</Type>
    </TypesNotToFlatten>
</ConfigModel>